{
    "clauseField": "11",
    "ftcCnclsns": "2",
    "clauseArticle": [
        "제22조(전자금융거래기록의 생성, 보존 및 파기) \n② 금융회사등은 제1항에 따라 보존하여야 하는 기간이 지나고 금융거래 등 상거래관계가 종료된 경우에는 5년 이내에 전자금융거래기록(신용정보의 이용 및 보호에 관한 법률에 따른 신용정보는 제외한다. 이하 이 항에서 같다)을 파기하여야 한다. 다만, 다음 각 호의 경우에는 그렇지 않다.\n2. 그 밖에 전자금융거래기록을 보관할 필요성이 있는 경우로서 금융위원회가 정하는 경우"
    ],
    "dvAntageous": "1",
    "comProvision": [
        "제22조(전자금융거래기록의 생성, 보존 및 파기) \n② 금융회사등은 제1항에 따라 보존하여야 하는 기간이 경과하고 금융거래 등 상거래관계가 종료된 경우에는 5년 이내에 전자금융거래기록(신용정보의 이용 및 보호에 관한 법률에 따른 신용정보는 제외한다. 이하 이 항에서 같다)을 파기하여야 한다. 다만, 다음 각 호의 경우에는 그러하지 아니하다.\n2. 그 밖에 전자금융거래기록을 보관할 필요성이 있는 경우로서 금융위원회가 정하는 경우"
    ]
}